{
  "0x123-example": {
    "platforms": {
      "chrome": {
        "install_link": "https://www.onflow.org"
      }
    }
  },
  "0x33f75ff0b830dcec": {
    "platforms": {
      "chrome": {
        "install_link": "https://chrome.google.com/webstore/detail/lilico/hpclkefagolihohboafpheddmmgdffjm"
      }
    }
  },
  "0x3d2b4d1b51f3a4cd": {
    "platforms": {
      "chrome": {
        "install_link": "https://chrome.google.com/webstore/detail/lilico/hpclkefagolihohboafpheddmmgdffjm"
      }
    }
  }
}
